LICENSE
MANIFEST.in
README.md
setup.cfg
setup.py
DoCodeStripe/__init__.py
DoCodeStripe/admin.py
DoCodeStripe/apps.py
DoCodeStripe/models.py
DoCodeStripe/urls.py
DoCodeStripe/views.py
DoCodeStripe/migrations/__init__.py
DoCodeStripe/migrations/__pycache__/__init__.cpython-37.pyc
DoCodeStripe/procesos/pago.py
DoCodeStripe/procesos/__pycache__/pago.cpython-37.pyc
DoCodeStripe/static/font-awesome-4.7.0/HELP-US-OUT.txt
DoCodeStripe/static/font-awesome-4.7.0/css/font-awesome.css
DoCodeStripe/static/font-awesome-4.7.0/css/font-awesome.min.css
DoCodeStripe/static/font-awesome-4.7.0/fonts/FontAwesome.otf
DoCodeStripe/static/font-awesome-4.7.0/fonts/fontawesome-webfont.eot
DoCodeStripe/static/font-awesome-4.7.0/fonts/fontawesome-webfont.svg
DoCodeStripe/static/font-awesome-4.7.0/fonts/fontawesome-webfont.ttf
DoCodeStripe/static/font-awesome-4.7.0/fonts/fontawesome-webfont.woff
DoCodeStripe/static/font-awesome-4.7.0/fonts/fontawesome-webfont.woff2
DoCodeStripe/static/font-awesome-4.7.0/less/animated.less
DoCodeStripe/static/font-awesome-4.7.0/less/bordered-pulled.less
DoCodeStripe/static/font-awesome-4.7.0/less/core.less
DoCodeStripe/static/font-awesome-4.7.0/less/fixed-width.less
DoCodeStripe/static/font-awesome-4.7.0/less/font-awesome.less
DoCodeStripe/static/font-awesome-4.7.0/less/icons.less
DoCodeStripe/static/font-awesome-4.7.0/less/larger.less
DoCodeStripe/static/font-awesome-4.7.0/less/list.less
DoCodeStripe/static/font-awesome-4.7.0/less/mixins.less
DoCodeStripe/static/font-awesome-4.7.0/less/path.less
DoCodeStripe/static/font-awesome-4.7.0/less/rotated-flipped.less
DoCodeStripe/static/font-awesome-4.7.0/less/screen-reader.less
DoCodeStripe/static/font-awesome-4.7.0/less/stacked.less
DoCodeStripe/static/font-awesome-4.7.0/less/variables.less
DoCodeStripe/static/font-awesome-4.7.0/scss/_animated.scss
DoCodeStripe/static/font-awesome-4.7.0/scss/_bordered-pulled.scss
DoCodeStripe/static/font-awesome-4.7.0/scss/_core.scss
dj_DoCodeStripe.egg-info/PKG-INFO
dj_DoCodeStripe.egg-info/SOURCES.txt
dj_DoCodeStripe.egg-info/dependency_links.txt
dj_DoCodeStripe.egg-info/top_level.txt