Metadata-Version: 2.1
Name: dj-DoCodeStripe
Version: 1.1.6
Summary: Basic Stripe configuration.
Home-page: https://github.com/DoCodeSoft
Author: DoCode
Author-email: aurea@docode.com.mx,mario@docode.com.mx,elias@docode.com.mx
License: MIT
Platform: UNKNOWN
Classifier: Environment :: Web Environment
Classifier: Framework :: Django
Classifier: Intended Audience :: Developers
Classifier: License :: OSI Approved :: BSD License
Classifier: Operating System :: OS Independent
Classifier: Programming Language :: Python
Classifier: Topic :: Internet :: WWW/HTTP
